haystack_integrations/components/generators/py.typed
haystack_integrations/components/generators/llama_cpp/__init__.py
haystack_integrations/components/generators/llama_cpp/generator.py
haystack_integrations/components/generators/llama_cpp/chat/chat_generator.py
llama_cpp_haystack-2.1.0.dist-info/METADATA
llama_cpp_haystack-2.1.0.dist-info/WHEEL
llama_cpp_haystack-2.1.0.dist-info/licenses/LICENSE.txt
llama_cpp_haystack-2.1.0.dist-info/RECORD
